monitio
