Metadata-Version: 1.1
Name: django-monitio
Version: 0.3.1
Summary: Unified, persistent and dynamic user messages/notifications for Django
Home-page: http://github.com/mpasternak/django-monitio
Author: mpasternak
Author-email: UNKNOWN
License: BSD
Keywords: messages,django,persistent,sse
Platform: UNKNOWN
Classifier: Development Status :: 4 - Beta
Classifier: Environment :: Web Environment
Classifier: Intended Audience :: Developers
Classifier: License :: OSI Approved :: BSD License
Classifier: Operating System :: OS Independent
Classifier: Programming Language :: Python
Classifier: Framework :: Django
